LICENSE
pyproject.toml
setup.py
src/lib_testtoolkit_python.egg-info/PKG-INFO
src/lib_testtoolkit_python.egg-info/SOURCES.txt
src/lib_testtoolkit_python.egg-info/dependency_links.txt
src/lib_testtoolkit_python.egg-info/not-zip-safe
src/lib_testtoolkit_python.egg-info/requires.txt
src/lib_testtoolkit_python.egg-info/top_level.txt
src/test_data_management/__init__.py
src/test_data_management/collectors/__init__.py
src/test_data_management/collectors/allure_collector.py
src/test_data_management/collectors/cucumber_collector.py
src/test_data_management/collectors/junit_collector.py
src/test_data_management/collectors/nunit_collector.py
src/test_data_management/core/__init__.py
src/test_data_management/core/base_collector.py
src/test_data_management/core/base_provider.py
src/test_data_management/core/test_data_manager.py
src/test_data_management/providers/__init__.py
src/test_data_management/providers/testrail_provider.py
src/utils/__init__.py
src/utils/config_reader.py